concurrency_limit/__init__.py
concurrency_limit/_connections.py
concurrency_limit/configuration.py
concurrency_limit/context_managers.py
concurrency_limit/exceptions.py
concurrency_limit/utils.py
concurrency_limit-1.1.1.dist-info/LICENSE
concurrency_limit-1.1.1.dist-info/METADATA
concurrency_limit-1.1.1.dist-info/WHEEL
concurrency_limit-1.1.1.dist-info/top_level.txt
concurrency_limit-1.1.1.dist-info/RECORD
