Metadata-Version: 2.1
Name: concurrency-limit
Version: 1.1.1
Summary: A library that implements a distributed concurrency limiting mechanism using Redis as a backend.
Home-page: https://github.com/anexia/python-concurrency-limit
Author: Andreas Stocker
Author-email: AStocker@anexia.com
License: MIT
Classifier: Development Status :: 5 - Production/Stable
Classifier: Intended Audience :: Developers
Classifier: License :: OSI Approved :: MIT License
Classifier: Operating System :: OS Independent
Classifier: Programming Language :: Python
Classifier: Programming Language :: Python :: 3
Classifier: Programming Language :: Python :: 3.9
Classifier: Programming Language :: Python :: 3.10
Classifier: Programming Language :: Python :: 3.11
Classifier: Programming Language :: Python :: 3.12
Classifier: Topic :: Software Development
License-File: LICENSE
Requires-Dist: redis >=4.0
